varaha/__init__.py
varaha/condor.py
varaha/detectors.py
varaha/functions.py
varaha/gnobs.py
varaha/inputs.py
varaha/parameter_estimation.py
varaha/utils.py
varaha/version_helper.py
varaha/weighted_kde.py
varaha/bin/__init__.py
varaha/bin/fast_pe.py
varaha-0.0.1.dist-info/LICENSE.md
varaha-0.0.1.dist-info/METADATA
varaha-0.0.1.dist-info/WHEEL
varaha-0.0.1.dist-info/entry_points.txt
varaha-0.0.1.dist-info/top_level.txt
varaha-0.0.1.dist-info/RECORD
