Metadata-Version: 2.1
Name: varaha
Version: 0.0.1
Summary: A Fast Non-Markovian Parameter Sampler for Coalescing Compact Binaries
Home-page: https://git.ligo.org/charlie.hoy/varaha
Author: Vaibhav Tiwari, Charlie Hoy, Stephen Fairhurst
Author-email: vaibhav.tiwari@ligo.org, charlie.hoy@ligo.org, stephen.fairhurst@ligo.org
License: MIT
Download-URL: https://git.ligo.org/charlie.hoy/varaha
Platform: UNKNOWN
Classifier: Programming Language :: Python :: 3.5
Classifier: Programming Language :: Python :: 3.6
Classifier: Programming Language :: Python :: 3.7
Requires-Dist: pycbc
Requires-Dist: numpy
Requires-Dist: scipy
Requires-Dist: gwpy
Requires-Dist: matplotlib
Requires-Dist: astropy
Requires-Dist: ligo-gracedb
Requires-Dist: lalsuite
Requires-Dist: pesummary
Requires-Dist: tqdm
